<reportSuite>
    <reports>
        <report tableName = "t_video_sdk_flow_h"
				keyFields = "projectid,networktype,platformid,htime" 
				period = "hourly" timeFormat = "yyyyMMddHH" timeField = "htime">
            <fieldDefinition>
                <field name="projectid" regular="[0-9a-zA-Z./-]*"/>
				<field name="networktype" regular="[0-9a-zA-Z./-]*"/>
				<field name="platformid" regular="[0-9a-zA-Z./-]*"/>
                <field name="htime"  regular="[0-9a-zA-Z./-]*"/>
            </fieldDefinition>
            <dimensions>
                <dimension id = "0" >
                    <reportIndex>
						video.sdk.flow.hoursflow.h
                    </reportIndex>
                </dimension>
                <dimension id = "0" >
                    <reportIndex>
						video.sdk.flow.totalavgflow.h,
						video.sdk.flow.hoursflow.hw
                    </reportIndex>
                </dimension>
                <dimension id = "0" >
                    <reportIndex>
						video.sdk.flow.totalavgflow.hw
                    </reportIndex>
                </dimension>
            </dimensions>
        </report>
    </reports>
</reportSuite>
<!--
相应index请查看

video_users_hours_action_index_h.xml
-->
